LICENSE
setup.py
lcmtools/__init__.py
lcmtools/__version__.py
lcmtools/lcmtools.py
lcmtools.egg-info/PKG-INFO
lcmtools.egg-info/SOURCES.txt
lcmtools.egg-info/dependency_links.txt
lcmtools.egg-info/requires.txt
lcmtools.egg-info/top_level.txt