Metadata-Version: 2.1
Name: lcmtools
Version: 0.1.3
Summary: A script that calls LCModel through Python.
Home-page: https://github.com/luodeb/lcmtools
Author: Luo Debin
Author-email: luodeb@qq.com
License: MIT
Classifier: License :: OSI Approved :: MIT License
Classifier: Programming Language :: Python
Classifier: Programming Language :: Python :: 3
Classifier: Programming Language :: Python :: 3.6
Classifier: Programming Language :: Python :: Implementation :: CPython
Classifier: Programming Language :: Python :: Implementation :: PyPy
Requires-Python: >=3.6.0
License-File: LICENSE
